{
  "formatted_phone_number" : "(218) 628-3691",
  "html_attributions" : [

  ],
  "url" : "https:\/\/maps.google.com\/?cid=8874131874060747871",
  "reference" : "CmRRAAAAurFIeY3KKGJ6YmyYqk623PNngIrR0sm55DJxygyXd5zvgG9eIR8BO9QuUMjxiwTQIKOnpMo8Pl-oB29onbsAVjWIfUCKFDdpkNu6NNlmLeAWXDpOWsbRs70b4jVy5malEhDTfR9VFcaly3FN750Z-h6TGhSbeBsMv6Qdz-Fso16fNubK831aUg",
  "opening_hours" : {
    "periods" : [
      {
        "open" : {
          "hours" : 0,
          "minutes" : 0,
          "day" : 0,
          "time" : "0000",
          "nextDate" : 1507438800000
        }
      }
    ],
    "weekday_text" : [
      "Monday: Open 24 hours",
      "Tuesday: Open 24 hours",
      "Wednesday: Open 24 hours",
      "Thursday: Open 24 hours",
      "Friday: Open 24 hours",
      "Saturday: Open 24 hours",
      "Sunday: Open 24 hours"
    ],
    "open_now" : true
  },
  "address_components" : [
    {
      "types" : [
        "street_number"
      ],
      "long_name" : "9315",
      "short_name" : "9315"
    },
    {
      "types" : [
        "route"
      ],
      "long_name" : "Westgate Boulevard",
      "short_name" : "Westgate Blvd"
    },
    {
      "types" : [
        "locality",
        "political"
      ],
      "long_name" : "Duluth",
      "short_name" : "Duluth"
    },
    {
      "types" : [
        "administrative_area_level_2",
        "political"
      ],
      "long_name" : "St. Louis County",
      "short_name" : "St Louis County"
    },
    {
      "types" : [
        "administrative_area_level_1",
        "political"
      ],
      "long_name" : "Minnesota",
      "short_name" : "MN"
    },
    {
      "types" : [
        "country",
        "political"
      ],
      "long_name" : "United States",
      "short_name" : "US"
    },
    {
      "types" : [
        "postal_code"
      ],
      "long_name" : "55810",
      "short_name" : "55810"
    }
  ],
  "icon" : "https:\/\/maps.gstatic.com\/mapfiles\/place_api\/icons\/lodging-71.png",
  "international_phone_number" : "+1 218-628-3691",
  "adr_address" : "<span class=\"street-address\">9315 Westgate Blvd<\/span>, <span class=\"locality\">Duluth<\/span>, <span class=\"region\">MN<\/span> <span class=\"postal-code\">55810<\/span>, <span class=\"country-name\">USA<\/span>",
  "formatted_address" : "9315 Westgate Blvd, Duluth, MN 55810, USA",
  "name" : "Americas Best Value Inn - Duluth Spirit Mountain Inn",
  "reviews" : [
    {
      "rating" : 4,
      "time" : 1506306976,
      "profile_photo_url" : "https:\/\/lh5.googleusercontent.com\/-S-1ty0__ahQ\/AAAAAAAAAAI\/AAAAAAAAAAA\/ACnBePZ7okcQWa8A_skNrGGZ1qPIF9JDng\/s128-c0x00000000-cc-rp-mo\/photo.jpg",
      "text" : "For the price is exactly what we were looking for. The beds are pretty firm so not the best for side sleepers. The staff has been really nice. Everything was clean. It was nice that there was a microwave and fridge in the room.",
      "language" : "en",
      "author_url" : "https:\/\/www.google.com\/maps\/contrib\/117806993749354447305\/reviews",
      "author_name" : "Justine Widmer",
      "relative_time_description" : "a week ago"
    },
    {
      "rating" : 4,
      "time" : 1502368474,
      "profile_photo_url" : "https:\/\/lh3.googleusercontent.com\/--etYvfUyNHA\/AAAAAAAAAAI\/AAAAAAAAAbc\/fmp-4d2N_ic\/s128-c0x00000000-cc-rp-mo-ba2\/photo.jpg",
      "text" : "Prob best check in experience, really friendly staff. Great price for the hotel, good value with amenities. Our room was right off the pool, so a little loud with people in pool and all, but we're pretty easy going. Rooms we fairly clean couple areas could have been cleaner. (Some like mold or calcium deposits on faucets that could have used a bleaching) other than that good stay.",
      "language" : "en",
      "author_url" : "https:\/\/www.google.com\/maps\/contrib\/107777140222668409126\/reviews",
      "author_name" : "Jake H",
      "relative_time_description" : "a month ago"
    },
    {
      "rating" : 5,
      "time" : 1506305175,
      "profile_photo_url" : "https:\/\/lh5.googleusercontent.com\/-aicyVG7EeCM\/AAAAAAAAAAI\/AAAAAAAAafM\/beZe4GKEsdo\/s128-c0x00000000-cc-rp-mo-ba2\/photo.jpg",
      "text" : "It was quite a bit cheaper than most of the hotels in Duluth, and is only about a five minute drive from downtown. The staff was extremely nice and accommodating. Having a room facing south provided great views towards the city and lake. The breakfast wasn't bad, with waffle makers, yogurt, cereal, and juice.",
      "language" : "en",
      "author_url" : "https:\/\/www.google.com\/maps\/contrib\/104926132964701308382\/reviews",
      "author_name" : "Spencer Hilgers",
      "relative_time_description" : "a week ago"
    },
    {
      "rating" : 3,
      "time" : 1505700165,
      "profile_photo_url" : "https:\/\/lh5.googleusercontent.com\/-LVeSoz-awFw\/AAAAAAAAAAI\/AAAAAAAAAAA\/ACnBePZFPtoUiUuNxFE7ic9Y6ooU6DbWdQ\/s128-c0x00000000-cc-rp-mo\/photo.jpg",
      "text" : "Hotel was ok. Parking was odd. Pool and hot tub are in 2 different rooms. Beds were overly firm for us. Not all rooms have same set up. Some have table with chairs for eating, others have just an armchair. Breakfast, eh, take it or leave it. Keep eye out for hidden charges....... Extra charge to use the hair dryer! And charges for using the safe that they leave in the room even if you don't use it.",
      "language" : "en",
      "author_url" : "https:\/\/www.google.com\/maps\/contrib\/113254449392719422883\/reviews",
      "author_name" : "Betsy Telecky",
      "relative_time_description" : "2 weeks ago"
    },
    {
      "rating" : 3,
      "time" : 1500053419,
      "profile_photo_url" : "https:\/\/lh4.googleusercontent.com\/-7WmAMOO0PeI\/AAAAAAAAAAI\/AAAAAAAAAAA\/ACnBePZw5NN5MvB4CKi2zRo0aDT2yog4rg\/s128-c0x00000000-cc-rp-mo\/photo.jpg",
      "text" : "Rooms decent but FAR from noise proof. You hear everything. Poor customer service at front desk at check in time. She was on the phone taking  reservation after reservation while they waited in line, Only to find out the room was not ready. The receptionist told me she would call me back when the room was done. Never called back, I had to call them. One of the more inexpensive hotels in Duluth, remember you get what you pay for",
      "language" : "en",
      "author_url" : "https:\/\/www.google.com\/maps\/contrib\/111977838102218574176\/reviews",
      "author_name" : "Michael wright",
      "relative_time_description" : "2 months ago"
    }
  ],
  "utc_offset" : -300,
  "types" : [
    "lodging",
    "point_of_interest",
    "establishment"
  ],
  "id" : "0a3ba894ce973e65a0ce192b6a85435218eb9c30",
  "scope" : "GOOGLE",
  "geometry" : {
    "viewport" : {
      "south" : 46.7254889197085,
      "north" : 46.7281868802915,
      "east" : -92.2184953197085,
      "west" : -92.22119328029152
    },
    "location" : {
      "lat" : 46.72710980000001,
      "lng" : -92.21990479999999
    }
  },
  "website" : "https:\/\/www.redlion.com\/duluth",
  "place_id" : "ChIJmXpl8t9LrlIRX8RcG-w_J3s",
  "photos" : [
    {
      "width" : 1024,
      "html_attributions" : [
        "<a href=\"https:\/\/maps.google.com\/maps\/contrib\/111078564689316653593\/photos\">Americas Best Value Inn - Duluth Spirit Mountain Inn<\/a>"
      ],
      "height" : 576
    },
    {
      "width" : 1024,
      "html_attributions" : [
        "<a href=\"https:\/\/maps.google.com\/maps\/contrib\/111078564689316653593\/photos\">Americas Best Value Inn - Duluth Spirit Mountain Inn<\/a>"
      ],
      "height" : 682
    },
    {
      "width" : 1024,
      "html_attributions" : [
        "<a href=\"https:\/\/maps.google.com\/maps\/contrib\/111078564689316653593\/photos\">Americas Best Value Inn - Duluth Spirit Mountain Inn<\/a>"
      ],
      "height" : 682
    },
    {
      "width" : 2988,
      "html_attributions" : [
        "<a href=\"https:\/\/maps.google.com\/maps\/contrib\/113511772660000871891\/photos\">Dustin Bickford<\/a>"
      ],
      "height" : 3984
    },
    {
      "width" : 1024,
      "html_attributions" : [
        "<a href=\"https:\/\/maps.google.com\/maps\/contrib\/111078564689316653593\/photos\">Americas Best Value Inn - Duluth Spirit Mountain Inn<\/a>"
      ],
      "height" : 466
    },
    {
      "width" : 600,
      "html_attributions" : [
        "<a href=\"https:\/\/maps.google.com\/maps\/contrib\/111078564689316653593\/photos\">Americas Best Value Inn - Duluth Spirit Mountain Inn<\/a>"
      ],
      "height" : 399
    },
    {
      "width" : 1024,
      "html_attributions" : [
        "<a href=\"https:\/\/maps.google.com\/maps\/contrib\/111078564689316653593\/photos\">Americas Best Value Inn - Duluth Spirit Mountain Inn<\/a>"
      ],
      "height" : 682
    },
    {
      "width" : 1024,
      "html_attributions" : [
        "<a href=\"https:\/\/maps.google.com\/maps\/contrib\/111078564689316653593\/photos\">Americas Best Value Inn - Duluth Spirit Mountain Inn<\/a>"
      ],
      "height" : 682
    },
    {
      "width" : 907,
      "html_attributions" : [
        "<a href=\"https:\/\/maps.google.com\/maps\/contrib\/111078564689316653593\/photos\">Americas Best Value Inn - Duluth Spirit Mountain Inn<\/a>"
      ],
      "height" : 680
    },
    {
      "width" : 890,
      "html_attributions" : [
        "<a href=\"https:\/\/maps.google.com\/maps\/contrib\/111078564689316653593\/photos\">Americas Best Value Inn - Duluth Spirit Mountain Inn<\/a>"
      ],
      "height" : 971
    }
  ],
  "vicinity" : "9315 Westgate Boulevard, Duluth",
  "rating" : 3.6
}
